controlmyspa/__init__.py
controlmyspa/controlmyspa.py
controlmyspa/debug.py
controlmyspa/example.py
controlmyspa/setup.py
controlmyspa-4.0.0.dist-info/licenses/LICENSE
controlmyspa-4.0.0.dist-info/METADATA
controlmyspa-4.0.0.dist-info/WHEEL
controlmyspa-4.0.0.dist-info/top_level.txt
controlmyspa-4.0.0.dist-info/RECORD
