Metadata-Version: 2.4
Name: controlmyspa
Version: 4.0.0
Summary: Balboa ControlMySpa™ cloud API for hot tub spa systems
Author-email: Aarno Aukia <aarno@aukia.com>
License: MIT
Project-URL: Homepage, https://github.com/arska/controlmyspa
Project-URL: Issues, https://github.com/arska/controlmyspa/issues
Keywords: Balboa,Controlmyspa,Whirlpool,API
Classifier: Programming Language :: Python :: 3
Classifier: License :: OSI Approved :: MIT License
Classifier: Operating System :: OS Independent
Classifier: Intended Audience :: Developers
Requires-Python: >=3.10
License-File: LICENSE
Requires-Dist: requests>2
Dynamic: license-file
